redstat/__init__.py
redstat/redload/__init__.py
redstat/redload/cli/__init__.py
redstat/redload/cli/arguments/__init__.py
redstat/redload/cli/arguments/positional/__init__.py
redstat/redload/cli/arguments/positional/name.py
redstat/redload/functions/__init__.py
redstat/redload/functions/download.py
redstat/redload/functions/save.py
redstat/redload/functions/validate.py
redstat/redload/variables/__init__.py
redstat/redload/variables/application.py
redstat/redload/variables/headers.py
redstat/redload/variables/url.py
redstat/shared_resources/__init__.py
redstat/shared_resources/cli/__init__.py
redstat/shared_resources/cli/defaults.py
redstat/shared_resources/cli/arguments/__init__.py
redstat/shared_resources/cli/arguments/types.py
redstat/shared_resources/cli/arguments/optional/__init__.py
redstat/shared_resources/cli/arguments/optional/output.py
redstat/shared_resources/cli/arguments/optional/verbose.py
redstat-2.1.0.dist-info/METADATA
redstat-2.1.0.dist-info/WHEEL
redstat-2.1.0.dist-info/entry_points.txt
redstat-2.1.0.dist-info/top_level.txt
redstat-2.1.0.dist-info/RECORD
