Metadata-Version: 2.1
Name: redstat
Version: 2.1.0
Summary: Cli tools for parse statistic from reddit
Author-email: temkuz <temkuz@yandex.ru>
Keywords: cli,reddit,parser,statistic
Requires-Python: >=3.11
Requires-Dist: aiohttp ==3.9.3
